LICENSE
MANIFEST.in
README.rst
setup.py
django_pybrowscap/__init__.py
django_pybrowscap/decorators.py
django_pybrowscap/middleware.py
django_pybrowscap/models.py
django_pybrowscap/settings.py
django_pybrowscap.egg-info/PKG-INFO
django_pybrowscap.egg-info/SOURCES.txt
django_pybrowscap.egg-info/dependency_links.txt
django_pybrowscap.egg-info/requires.txt
django_pybrowscap.egg-info/top_level.txt
django_pybrowscap/management/__init__.py
django_pybrowscap/management/commands/__init__.py
django_pybrowscap/management/commands/download_browscap.py
django_pybrowscap/tests/__init__.py
django_pybrowscap/tests/test_middleware.py
django_pybrowscap/tests/data/browscap_14_05_2012.csv
django_pybrowscap/tests/management/__init__.py
django_pybrowscap/tests/management/commands/__init__.py
django_pybrowscap/tests/management/commands/test_download_browscap.py