Metadata-Version: 1.1
Name: django-pybrowscap
Version: 1.0.0
Summary: django-pybrowscap is django middleware with support for pybrowscap
Home-page: http://www.codescale.net/en/community#django-pybrowscap
Author: Vladimír Gorej
Author-email: gorej@codescale.net
License: BSD
Download-URL: http://github.com/CodeScaleInc/django-pybrowscap/tarball/master
Keywords: browser browscap detection user agent django
Platform: any
Classifier: Development Status :: 4 - Beta
Classifier: Environment :: Web Environment
Classifier: Intended Audience :: Developers
Classifier: Intended Audience :: System Administrators
Classifier: Intended Audience :: Information Technology
Classifier: License :: OSI Approved :: BSD License
Classifier: Operating System :: OS Independent
Classifier: Programming Language :: Python
Classifier: Topic :: Utilities
Classifier: Topic :: Internet :: WWW/HTTP
Classifier: Topic :: Internet :: WWW/HTTP :: Browsers
